universal_encryptor/GUI.py
universal_encryptor/__init__.py
universal_encryptor/crypt.py
universal_encryptor/file_detection.py
universal_encryptor/key_file.py
universal_encryptor/log.py
universal_encryptor-0.1.0.dist-info/METADATA
universal_encryptor-0.1.0.dist-info/WHEEL
universal_encryptor-0.1.0.dist-info/licenses/LICENSE
universal_encryptor-0.1.0.dist-info/RECORD
