Metadata-Version: 2.4
Name: universal_encryptor
Version: 0.1.0
Summary: Universal file encryptor and decryptor with GUI
Author-email: Jean Cotto <jccs22_26@outlook.com>
License: MIT
License-File: LICENSE
Requires-Python: >=3.8
Requires-Dist: cryptography
Requires-Dist: customtkinter
Requires-Dist: filetype
Requires-Dist: pillow
